supercells/__init__.py
supercells/__main__.py
supercells/config.py
supercells/main.py
supercells/version.py
supercells/modules/__init__.py
supercells/modules/cellranger.py
supercells/modules/general.py
supercells-0.0.5.dist-info/LICENSE
supercells-0.0.5.dist-info/METADATA
supercells-0.0.5.dist-info/WHEEL
supercells-0.0.5.dist-info/entry_points.txt
supercells-0.0.5.dist-info/top_level.txt
supercells-0.0.5.dist-info/RECORD
