Metadata-Version: 2.1
Name: supercells
Version: 0.0.5
Summary: Easily assess quality control data across multiple single cell datasets
Home-page: https://github.com/compugen-ltd/supercells
Author: Compugen LTD
Author-email: royg@cgen.com
Classifier: Programming Language :: Python :: 3
Classifier: License :: OSI Approved :: BSD License
Classifier: Operating System :: OS Independent
Requires-Python: >=3.7
License-File: LICENSE
Requires-Dist: pandas ==2.2
Requires-Dist: plotly ==5.20
Requires-Dist: Jinja2 ==3.1.3
Requires-Dist: openpyxl ==3.1.2
